stacking_2d_systems/__init__.py
stacking_2d_systems/auto_stack.py
stacking_2d_systems/cli.py
stacking_2d_systems/file_typer.py
stacking_2d_systems/slip_layers.py
stacking_2d_systems-0.1.3.dist-info/METADATA
stacking_2d_systems-0.1.3.dist-info/WHEEL
stacking_2d_systems-0.1.3.dist-info/entry_points.txt
stacking_2d_systems-0.1.3.dist-info/RECORD
