Metadata-Version: 2.1
Name: stacking-2d-systems
Version: 0.1.3
Summary: A python package for creating stack layers of 2D systems.
License: MIT
Keywords: 2D materials,stacking,AA stacking,AB stacking,slip stacking,COFs,crystal structures,Graphene
Author: Dinga Wonanke
Author-email: bafgreat@gmail.com
Requires-Python: >=3.9,<4.0
Classifier: License :: OSI Approved :: MIT License
Classifier: Programming Language :: Python :: 3
Classifier: Programming Language :: Python :: 3.9
Classifier: Programming Language :: Python :: 3.10
Classifier: Programming Language :: Python :: 3.11
Classifier: Programming Language :: Python :: 3.12
Requires-Dist: ase (>=3.23.0,<4.0.0)
Requires-Dist: gulp_setup (>=0.1.5,<0.2.0)
Requires-Dist: openpyxl (>=3.1.5,<4.0.0)
Requires-Dist: pytest (>=8.3.3,<9.0.0)
